json_repair_llm/__init__.py
json_repair_llm/json_repair.py
json_repair_llm-0.1.0.dist-info/METADATA
json_repair_llm-0.1.0.dist-info/WHEEL
json_repair_llm-0.1.0.dist-info/licenses/LICENSE
json_repair_llm-0.1.0.dist-info/RECORD
