Metadata-Version: 2.4
Name: json_repair_llm
Version: 0.1.0
Summary: JSON repair using multiple backends: LLMs and FSM-based processing with Pydantic models
Project-URL: Homepage, https://github.com/imvladikon/json-repair-llm
Project-URL: Bug Tracker, https://github.com/imvladikon/json-repair-llm/issues
Author-email: Vladimir Gurevich <imvladikon@gmail.com>
License: MIT License
License-File: LICENSE
Classifier: Intended Audience :: Developers
Classifier: License :: OSI Approved :: MIT License
Classifier: Operating System :: OS Independent
Classifier: Programming Language :: Python :: 3
Classifier: Programming Language :: Python :: 3.10
Classifier: Programming Language :: Python :: 3.11
Classifier: Topic :: Software Development :: Libraries :: Python Modules
Requires-Python: >=3.10
Requires-Dist: accelerate
Requires-Dist: bitsandbytes
Requires-Dist: jinja2
Requires-Dist: json-repair
Requires-Dist: loguru
Requires-Dist: outlines[transformers]
Requires-Dist: pydantic<3.0.0,>=2.10.0
Requires-Dist: sentencepiece
Requires-Dist: torch
Requires-Dist: transformers
Provides-Extra: dev
Requires-Dist: build; extra == 'dev'
Requires-Dist: isort; extra == 'dev'
Requires-Dist: mypy; extra == 'dev'
Requires-Dist: pytest; extra == 'dev'
Requires-Dist: ruff; extra == 'dev'
Requires-Dist: setuptools; extra == 'dev'
Requires-Dist: twine; extra == 'dev'
Requires-Dist: wheel; extra == 'dev'
Provides-Extra: fsm
Requires-Dist: transitions; extra == 'fsm'
Provides-Extra: full
Requires-Dist: flash-attn; extra == 'full'
Requires-Dist: transitions; extra == 'full'
